DownloadKit/__init__.py
DownloadKit/_funcs.py
DownloadKit/_funcs.pyi
DownloadKit/downloadKit.py
DownloadKit/downloadKit.pyi
DownloadKit/mission.py
DownloadKit/mission.pyi
DownloadKit/setter.py
DownloadKit/setter.pyi
DrissionDownloader-2.0.0.dist-info/LICENSE
DrissionDownloader-2.0.0.dist-info/METADATA
DrissionDownloader-2.0.0.dist-info/WHEEL
DrissionDownloader-2.0.0.dist-info/top_level.txt
DrissionDownloader-2.0.0.dist-info/RECORD
