Metadata-Version: 2.1
Name: DrissionDownloader
Version: 2.0.0
Summary: 一个简洁易用的多线程文件下载工具。
Home-page: https://gitee.com/g1879/DownloadKit
Author: g1879
Author-email: g1879@qq.com
License: BSD
Keywords: DrissionDownloader
Classifier: Programming Language :: Python :: 3.6
Classifier: Development Status :: 4 - Beta
Classifier: Topic :: Utilities
Classifier: License :: OSI Approved :: BSD License
Requires-Python: >=3.6
License-File: LICENSE
Requires-Dist: requests
Requires-Dist: DataRecorder (>=3.4.11)
